balancing_services/__init__.py
balancing_services/client.py
balancing_services/errors.py
balancing_services/types.py
balancing_services/api/__init__.py
balancing_services/api/default/__init__.py
balancing_services/api/default/get_balancing_capacity_bids.py
balancing_services/api/default/get_balancing_capacity_prices.py
balancing_services/api/default/get_balancing_capacity_procured_volumes.py
balancing_services/api/default/get_balancing_energy_activated_volumes.py
balancing_services/api/default/get_balancing_energy_bids.py
balancing_services/api/default/get_balancing_energy_offered_volumes.py
balancing_services/api/default/get_balancing_energy_prices.py
balancing_services/api/default/get_cross_zonal_capacity_allocation.py
balancing_services/api/default/get_imbalance_prices.py
balancing_services/api/default/get_imbalance_total_volumes.py
balancing_services/models/__init__.py
balancing_services/models/activation_type.py
balancing_services/models/area.py
balancing_services/models/balancing_capacity_bids.py
balancing_services/models/balancing_capacity_bids_response.py
balancing_services/models/balancing_capacity_price.py
balancing_services/models/balancing_capacity_prices.py
balancing_services/models/balancing_capacity_prices_response.py
balancing_services/models/balancing_capacity_volume.py
balancing_services/models/balancing_capacity_volumes.py
balancing_services/models/balancing_capacity_volumes_response.py
balancing_services/models/balancing_energy_bids.py
balancing_services/models/balancing_energy_bids_response.py
balancing_services/models/balancing_energy_price.py
balancing_services/models/balancing_energy_prices.py
balancing_services/models/balancing_energy_prices_response.py
balancing_services/models/balancing_energy_volume.py
balancing_services/models/balancing_energy_volumes.py
balancing_services/models/balancing_energy_volumes_response.py
balancing_services/models/bid_status.py
balancing_services/models/capacity_bid.py
balancing_services-1.6.0.dist-info/METADATA
balancing_services-1.6.0.dist-info/WHEEL
balancing_services-1.6.0.dist-info/licenses/LICENSE
balancing_services-1.6.0.dist-info/RECORD
