Metadata-Version: 2.4
Name: balancing-services
Version: 1.6.0
Summary: Official Python client for accessing European electricity balancing market data via the Balancing Services REST API
Project-URL: Homepage, https://balancing.services
Project-URL: Documentation, https://api.balancing.services/v1/documentation
Project-URL: Repository, https://github.com/balancing-services/rest-api
Project-URL: Changelog, https://github.com/balancing-services/rest-api/blob/main/CHANGELOG.md
Author: Balancing Services Team
License: MIT
License-File: LICENSE
Keywords: FCR,aFRR,api,balancing,electricity,energy,europe,grid,imbalance,mFRR,market,openapi,power,reserves
Classifier: Development Status :: 4 - Beta
Classifier: Intended Audience :: Developers
Classifier: License :: OSI Approved :: MIT License
Classifier: Programming Language :: Python :: 3
Classifier: Programming Language :: Python :: 3.10
Classifier: Programming Language :: Python :: 3.11
Classifier: Programming Language :: Python :: 3.12
Classifier: Programming Language :: Python :: 3.13
Classifier: Topic :: Software Development :: Libraries :: Python Modules
Classifier: Typing :: Typed
Requires-Python: >=3.10
Requires-Dist: attrs>=23.0.0
Requires-Dist: httpx<1.0.0,>=0.28.0
Requires-Dist: python-dateutil<3.0.0,>=2.9.0
Provides-Extra: dev
Requires-Dist: mypy>=1.8.0; extra == 'dev'
Requires-Dist: pytest-asyncio>=1.0.0; extra == 'dev'
Requires-Dist: pytest-cov>=6.0.0; extra == 'dev'
Requires-Dist: pytest>=8.0.0; extra == 'dev'
Requires-Dist: respx>=0.22.0; extra == 'dev'
Requires-Dist: ruff>=0.8.0; extra == 'dev'
Requires-Dist: types-python-dateutil>=2.9.0; extra == 'dev'
